Metadata-Version: 2.1
Name: stdget
Version: 1.1.2
Summary: A library to capture sys.stdout and -err
Home-page: https://github.com/CenTdemeern1/stdget
Author: CenTdemeern1
Author-email: timo.herngreen@gmail.com
License: UNKNOWN
Keywords: sys std stdout stderr get stdget sys.stdout sys.stderr capture
Platform: UNKNOWN
Classifier: Development Status :: 5 - Production/Stable
Classifier: Intended Audience :: Developers
Classifier: Topic :: Software Development
Classifier: Programming Language :: Python :: 2
Classifier: Programming Language :: Python :: 2.6
Classifier: Programming Language :: Python :: 2.7
Classifier: Programming Language :: Python :: 3
Classifier: Programming Language :: Python :: 3.1
Classifier: Programming Language :: Python :: 3.2
Classifier: Programming Language :: Python :: 3.3
Classifier: Programming Language :: Python :: 3.4
Classifier: Programming Language :: Python :: 3.5
Classifier: Programming Language :: Python :: 3.6
Classifier: Programming Language :: Python :: 3.7
